{
  "categories": {
    "N1": [
      "女装",
      "男装",
      "内衣",
      "配饰",
      "鞋",
      "箱包",
      "运动户外",
      "玩具童装",
      "办公文化",
      "宠物园艺",
      "美妆个护",
      "收纳清洁",
      "食品酒水",
      "餐饮生鲜",
      "日用餐厨",
      "居家日用",
      "家用电器",
      "数码电脑",
      "家装灯饰",
      "家纺家饰",
      "汽车用品",
      "工业用品"
    ],
    "underwear_N2": [
      "新中式",
      "汉服套装",
      "马面裙",
      "披帛",
      "云肩",
      "唐装套装",
      "唐装裙子",
      "唐装上衣",
      "唐装裤子",
      "中式连衣裙",
      "新中式马甲",
      "下装裤",
      "女式牛仔裤",
      "休闲裤",
      "女士短裤",
      "女士卫裤",
      "打底裤",
      "一体裤",
      "羽绒裤/棉裤",
      "西装裤/正装裤",
      "大码女装",
      "中老年装",
      "孕妇装",
      "内裤",
      "袜子",
      "文胸",
      "家居服",
      "情趣塑身",
      "胸贴背心"
    ],
    "underwear_N3": {
      "内裤": [
        "石墨烯内裤",
        "无痕内裤",
        "3D蜜桃臀内裤",
        "女士三角裤",
        "女士大码内裤",
        "女士平角裤",
        "女士丁字裤",
        "孕妇内裤",
        "女士安全裤",
        "女士生理裤",
        "本命年内裤",
        "男士平角裤",
        "男士阿罗裤",
        "男士大码内裤",
        "男士三角裤",
        "男士丁字裤",
        "男士U型内裤"
      ],
      "袜子": [
        "丝袜",
        "连裤打底踩脚袜",
        "半掌袜",
        "JK袜",
        "洛丽塔袜",
        "运动休闲棉袜",
        "船袜隐形袜",
        "地板袜",
        "商务袜",
        "堆堆袜",
        "美腿压力袜",
        "分趾袜",
        "鱼嘴露趾袜",
        "袜套",
        "睡眠袜",
        "玛丽珍鞋袜"
      ],
      "文胸": [
        "鱼骨马甲文胸",
        "运动文胸",
        "法式文胸",
        "软支撑文胸",
        "背心式文胸",
        "美背文胸",
        "大码文胸",
        "少女文胸",
        "隐形文胸",
        "哺乳文胸",
        "调整型文胸",
        "中老年文胸",
        "无痕文胸",
        "文胸套装",
        "无钢圈文胸",
        "孕妇内衣",
        "本命年文胸"
      ],
      "家居服": [
        "新中式家居服",
        "晨袍",
        "家居睡裤",
        "女士家居服",
        "男士家居服",
        "情侣家居服",
        "睡袍浴袍",
        "睡裙",
        "月子服/哺乳装",
        "桑拿/汗蒸服",
        "亲子家居服",
        "本命年家居服"
      ],
      "情趣塑身": [
        "塑身上衣",
        "塑身裤",
        "收腹收腰带",
        "塑身连体衣",
        "塑身分体套装",
        "束缚带/塑体衣/矫正带"
      ]
    }
  },
  "trending": {
    "hot_search": [
      "哈兰德头绳",
      "女孩新款游泳衣",
      "套装两件套洋气",
      "手链批货"
    ],
    "trending_topics": [
      "本地菜系专用小家电",
      "小家电源头工厂的高复购密码",
      "眼部拨筋小家电爆发",
      "足弓训练器爆单",
      "粤港风味快消伴手礼",
      "快消美妆一件代发",
      "双电压电吹风",
      "旅行小家电"
    ],
    "popular_keywords": [
      "橡皮擦",
      "偶氮颜料",
      "折射仪",
      "掌上游戏机",
      "雨刮器",
      "风琴包/文件包",
      "学习机",
      "建筑模型",
      "电饭煲",
      "油灰刀",
      "光学仪器",
      "板岩/文化石",
      "安全膜",
      "商用垃圾处理机",
      "女式棉鞋",
      "望远镜"
    ],
    "hot_products": [
      {
        "name": "指南针",
        "price": "0.31",
        "sales": "10万+"
      },
      {
        "name": "60mm不锈钢指南针",
        "price": "0.82",
        "sales": "10万+"
      },
      {
        "name": "航海指南针",
        "price": "9.99",
        "sales": "5.1万+"
      }
    ]
  },
  "stats": {
    "total_entries": 38281199,
    "new_yesterday": 180000
  }
}