{
  "offer_id": 598568750928,
  "mtop": {
    "title": "新款跨境家用充电便捷美容电动洗脸刷超声波多功能硅胶防水洗脸仪",
    "price_cny": 52.0,
    "shop": "艾尔电器科技有限公司",
    "image_url": "https://cbu01.alicdn.com/img/ibank/O1CN01kiiRQl20R3zaIUJJ4_!!3199766845-0-cib.jpg"
  },
  "su_detail": {},
  "rakumart": null,
  "enriched_at": "2026-06-24T06:25:30.061124Z",
  "category": "beauty_devices",
  "taxonomy": {
    "n1": "美妆护肤",
    "n2": "美容仪器",
    "n3": "",
    "n4": ""
  },
  "raw_data": {
    "booked": 3939,
    "province": "浙江",
    "repurchase_rate": "47%"
  }
}