{
  "offer_id": 656110491767,
  "mtop": {
    "title": "美人传计塑身连体后脱式内女束腰提臀合跨养护收腰收腹塑身连体衣",
    "price_cny": "24",
    "shop": "魅蓝之都内衣",
    "image_url": "https://cbu01.alicdn.com/img/ibank/O1CN01vhN4Hs1P5PGSlqScO_!!2212439421789-0-cib.jpg"
  },
  "su_detail": {},
  "rakumart": {
    "match_score": 46.3,
    "price_brl": 33.84,
    "title_br": "Body de alcinha com renda, modelador e sexy, igual ao da marca SKIM.",
    "url": "https://www.rakumart.com.br/product/863178855479"
  },
  "enriched_at": "2026-06-22T15:39:38.205840Z",
  "category": "underwear",
  "taxonomy": {
    "n1": "服装鞋帽",
    "n2": "内衣",
    "n3": "塑身衣",
    "n4": "收腹塑身"
  }
}