{
  "offer_id": 680779423096,
  "mtop": {
    "title": "光宸12线绿光水平仪高精度强光16线贴墙贴地仪红外线激光平水仪器",
    "price_cny": 79.2,
    "shop": "光宸科技2022",
    "image_url": "https://cbu01.alicdn.com/img/ibank/O1CN01nieTNL1wsIw8K8RAt_!!2214504666363-0-cib.jpg"
  },
  "su_detail": {},
  "rakumart": null,
  "enriched_at": "2026-06-24T19:43:25.214082Z",
  "category": "五金工具",
  "taxonomy": {
    "n1": "五金工具",
    "n2": "测量工具",
    "n3": "",
    "n4": ""
  },
  "raw_data": {
    "booked": 21636,
    "province": "江苏"
  }
}