{
  "offer_id": 753360216375,
  "mtop": {
    "title": "喷胶中性笔按动高颜值st头塑料广告笔logo定制商务办公文具礼品笔",
    "price_cny": 2.43,
    "shop": "笔业金牌供应商",
    "image_url": "https://cbu01.alicdn.com/img/ibank/O1CN01MxbhrM2EfdPRVZxdp_!!2222388772-0-cib.jpg"
  },
  "su_detail": {},
  "rakumart": null,
  "enriched_at": "2026-06-24T02:08:45.289297Z",
  "category": "stationery",
  "taxonomy": {
    "n1": "文具办公",
    "n2": "",
    "n3": "",
    "n4": ""
  },
  "raw_data": {
    "booked": 108,
    "province": "浙江",
    "repurchase_rate": "25%"
  }
}