{
  "offer_id": 836402757558,
  "mtop": {
    "title": "儿童防喷防胀气吸管学饮杯一瓶三用喝水喝奶吸管奶瓶厂家现货批发",
    "price_cny": 17.9,
    "shop": "皇星爱尼诺婴童用品",
    "image_url": "https://cbu01.alicdn.com/img/ibank/O1CN01bn0KVY27ZUnk4XEBu_!!2218621487811-0-cib.jpg"
  },
  "su_detail": {},
  "rakumart": null,
  "enriched_at": "2026-06-24T02:08:45.272766Z",
  "category": "baby",
  "taxonomy": {
    "n1": "母婴用品",
    "n2": "",
    "n3": "",
    "n4": ""
  },
  "raw_data": {
    "booked": 2433,
    "province": "广东",
    "repurchase_rate": "27%"
  }
}