{
  "offer_id": "850604225085",
  "category": "Iluminação",
  "enriched_at": "2026-06-25T21:15:35.285337",
  "mtop": {
    "title": "美式<font color=red>吊灯</font>现代简约客厅卧室餐厅<font color=red>吊灯</font>乡村复古布艺<font color=red>吊灯</font>复古中山灯具",
    "price_cny": 52.0,
    "shop": "",
    "image_url": "https://cbu01.alicdn.com/img/ibank/O1CN01wVGshw2IT2sD5Lyx7_!!3497299286-0-cib.jpg"
  },
  "su_detail": {},
  "rakumart": {},
  "taxonomy": {
    "n1": "电子数码",
    "n2": "照明",
    "n3": null,
    "n4": null
  }
}