{
  "offer_id": 861251038133,
  "mtop": {
    "title": "彩光冷热颈部按摩仪面部导入仪美颈仪家用电子美容仪脸部刮痧仪",
    "price_cny": 115.0,
    "shop": "中国卓一品",
    "image_url": "https://cbu01.alicdn.com/img/ibank/O1CN01AW6u3V2IKnrftPf9q_!!2723889268-0-cib.jpg"
  },
  "su_detail": {},
  "rakumart": null,
  "enriched_at": "2026-06-24T06:25:30.057468Z",
  "category": "beauty_devices",
  "taxonomy": {
    "n1": "美妆护肤",
    "n2": "美容仪器",
    "n3": "",
    "n4": ""
  },
  "raw_data": {
    "booked": 184,
    "province": "广东",
    "repurchase_rate": "40%"
  }
}