{
  "offer_id": 883606624444,
  "mtop": {
    "title": "浸塑哑铃女士健身家用男生青少年小学生儿童实心铸铁纯铁迷你小亚",
    "price_cny": 7.0,
    "shop": "江苏金桓健身器材有限公司",
    "image_url": "https://cbu01.alicdn.com/img/ibank/O1CN01kf3Wrw1Gyz897je7g_!!2214437810692-0-cib.jpg"
  },
  "su_detail": {},
  "rakumart": null,
  "enriched_at": "2026-06-24T19:43:25.227726Z",
  "category": "户外运动",
  "taxonomy": {
    "n1": "户外运动",
    "n2": "健身器材",
    "n3": "",
    "n4": ""
  },
  "raw_data": {
    "booked": 5705,
    "province": "江苏"
  }
}