{
  "offer_id": 904776439454,
  "mtop": {
    "title": "17cm试管装不锈钢串珠钩针引线穿珠神器侧开口专用手工饰品DIY项",
    "price_cny": 1.9,
    "shop": "玺晟贸易有限公司",
    "image_url": "https://cbu01.alicdn.com/img/ibank/O1CN01zKGbuR1sGySn8vFcN_!!2215955155740-0-cib.jpg"
  },
  "su_detail": {},
  "rakumart": null,
  "enriched_at": "2026-06-24T19:43:25.392466Z",
  "category": "家居日用",
  "taxonomy": {
    "n1": "家居日用",
    "n2": "客厅用品",
    "n3": "",
    "n4": ""
  },
  "raw_data": {
    "booked": 1810,
    "province": "浙江"
  }
}