{
  "offer_id": 909340143804,
  "mtop": {
    "title": "跨境304不锈钢保温杯男女同款双饮水果杯户外手提运动水壶现货",
    "price_cny": 17.5,
    "shop": "华熊五金制品厂",
    "image_url": "https://cbu01.alicdn.com/img/ibank/O1CN01nQvwgd1CSERAoDkVi_!!2219638330079-0-cib.jpg"
  },
  "su_detail": {},
  "rakumart": null,
  "enriched_at": "2026-06-24T06:25:30.088895Z",
  "category": "kitchen",
  "taxonomy": {
    "n1": "家居日用",
    "n2": "厨房用品",
    "n3": "",
    "n4": ""
  },
  "raw_data": {
    "booked": 1513,
    "province": "浙江",
    "repurchase_rate": "13%"
  }
}