{
  "offer_id": 919001169931,
  "mtop": {
    "title": "双屏显示器支架机械悬臂一拖二电脑显示屏幕二合一桌面底座支尔成",
    "price_cny": 179.0,
    "shop": "yuanfanmount",
    "image_url": "https://cbu01.alicdn.com/img/ibank/O1CN01Aq1RbM1YN7T6a9DK2_!!985813046-0-cib.jpg"
  },
  "su_detail": {},
  "rakumart": null,
  "enriched_at": "2026-06-24T19:43:25.419972Z",
  "category": "电子数码",
  "taxonomy": {
    "n1": "电子数码",
    "n2": "电脑配件",
    "n3": "",
    "n4": ""
  },
  "raw_data": {
    "booked": 112,
    "province": "浙江"
  }
}